errors.py
ftp.py
ftp_proxy.py
sftp.py
utils.py
ftp_proxy-0.0.18.dist-info/LICENSE
ftp_proxy-0.0.18.dist-info/METADATA
ftp_proxy-0.0.18.dist-info/WHEEL
ftp_proxy-0.0.18.dist-info/entry_points.txt
ftp_proxy-0.0.18.dist-info/top_level.txt
ftp_proxy-0.0.18.dist-info/RECORD
