Metadata-Version: 2.1
Name: ftp-proxy
Version: 0.0.18
Summary: A http to ftp proxy server application
Home-page: https://github.com/uptilab2/ftp_proxy
Author: Emile Caron
Author-email: emile.caron@outlook.com
License: UNKNOWN
Project-URL: Source, https://github.com/uptilab2/ftp_proxy
Keywords: ftp proxy
Platform: UNKNOWN
Classifier: Development Status :: 3 - Alpha
Classifier: Intended Audience :: Developers
Classifier: Topic :: Software Development :: Build Tools
Classifier: License :: OSI Approved :: MIT License
Classifier: Programming Language :: Python :: 3.6
Requires-Dist: aiohttp
Requires-Dist: aioftp
Requires-Dist: asyncssh
Provides-Extra: dev
Requires-Dist: pytest ; extra == 'dev'
Requires-Dist: pytest-aiohttp ; extra == 'dev'
Requires-Dist: flake8 ; extra == 'dev'
